kanchi_sdk/__init__.py
kanchi_sdk/progress.py
kanchi_sdk/task_mixin.py
kanchi_sdk-0.0.1.dist-info/WHEEL
kanchi_sdk-0.0.1.dist-info/METADATA
kanchi_sdk-0.0.1.dist-info/RECORD
