Metadata-Version: 2.3
Name: kanchi-sdk
Version: 0.0.1
Summary: Lightweight SDK for emitting Kanchi-compatible Celery events.
Author: Kanchi
License: MIT License
Classifier: Development Status :: 3 - Alpha
Classifier: Intended Audience :: Developers
Classifier: License :: OSI Approved :: MIT License
Classifier: Programming Language :: Python
Classifier: Programming Language :: Python :: 3
Classifier: Programming Language :: Python :: 3 :: Only
Classifier: Programming Language :: Python :: 3.9
Classifier: Programming Language :: Python :: 3.10
Classifier: Programming Language :: Python :: 3.11
Classifier: Programming Language :: Python :: 3.12
Classifier: Programming Language :: Python :: 3.13
Classifier: Programming Language :: Python :: 3.14
Classifier: Topic :: Software Development
Requires-Dist: celery>=5
Requires-Dist: celery>=5 ; extra == 'dev'
Requires-Dist: pytest>=7.4 ; extra == 'dev'
Requires-Dist: pytest-cov>=4.1 ; extra == 'dev'
Requires-Dist: ruff>=0.1.9 ; extra == 'dev'
Requires-Dist: mypy>=1.8.0 ; extra == 'dev'
Requires-Python: >=3.9
Project-URL: Homepage, https://kanchi.io
Project-URL: Issues, https://github.com/getkanchi/kanchi-sdk/issues
Project-URL: Source, https://github.com/getkanchi/kanchi-sdk
Provides-Extra: dev
